{
  "udtType": "Page",
  "parameters": {
    "title": "Avoid Being Fractally Wrong",
    "slug": "app-avoid-being-fractally-wrong",
    "route": "/whitepapers/avoid-being-fractally-wrong",
    "view": "guild/apps/whitepapers/views/white-paper-app.view.json",
    "data": {
      "paper": "guild/apps/whitepapers/data/avoid-being-fractally-wrong.data.json"
    },
    "stylesheets": [
      "guild/Enterprise/L2/hmi/web/style/main.css"
    ],
    "section": "resources",
    "parent_slug": "white-papers",
    "status": "published"
  },
  "tags": {
    "id": "app-avoid-being-fractally-wrong",
    "view_id": "white-paper-app",
    "schema_version": "1.0.0"
  }
}